Metadata-Version: 1.0
Name: dsnd-probability-gk
Version: 0.1
Summary: Gaussian distributions
Home-page: UNKNOWN
Author: Kishore
Author-email: UNKNOWN
License: UNKNOWN
Platform: UNKNOWN
